avt_fresh/__init__.py
avt_fresh/api.py
avt_fresh/client.py
avt_fresh/invoice.py
avt_fresh/payments.py
avt_fresh/token.py
avt_fresh-0.0.17.dist-info/LICENSE.txt
avt_fresh-0.0.17.dist-info/METADATA
avt_fresh-0.0.17.dist-info/WHEEL
avt_fresh-0.0.17.dist-info/top_level.txt
avt_fresh-0.0.17.dist-info/RECORD
