Metadata-Version: 2.1
Name: avt-fresh
Version: 0.0.17
Summary: A nice, ergonomic wrapper of the Freshbooks API.
Home-page: https://github.com/zevaverbach/avt-fresh
Author: Zev Averbach
Author-email: zev@averba.ch
License: MIT
Keywords: freshbooks API
Requires-Python: >3.10.0
License-File: LICENSE.txt
Requires-Dist: requests
Requires-Dist: redis
